<?xml version="1.0" encoding="UTF-8"?>
<configuration>
	<property>
		<name>javax.jdo.option.ConnectionURL</name>
		<value>jdbc:mysql://hadoop01:3306/hive?createDatabaseIfNotExist=true</value>
	</property>
	<property>
		<name>javax.jdo.option.ConnectionDriverName</name>
		<value>com.mysql.cj.jdbc.Driver</value>
	</property>
	<property>
		<name>javax.jdo.option.ConnectionUserName</name>
		<value>root</value>
	</property>
	<property>
		<name>javax.jdo.option.ConnectionPassword</name>
		<value>Lz19970222!</value>
	</property>
	<property>
		<name>hive.server2.active.passive.ha.enable</name>
		<value>true</value>
	</property>
	<property>
		<name>hive.log.explain.output</name>
		<value>true</value>
	</property>
    <property>
        <name>hive.metastore.uris</name>
        <value>thrift://hadoop01:9083</value>
    </property>
    <property>
        <name>hive.metastore.schema.verification</name>
        <value>true</value>
    </property>
</configuration>
